[
  {
    "name": "visible",
    "type": "Boolean",
    "initValue": true,
    "locale": {
      "zh": "可见"
    }
  },
  {
    "name": "enabledClassName",
    "type": "Boolean",
    "initValue": false,
    "groupName": "自定义样式",
    "affectPropsShow": true,
    "locale": {
      "zh": "类名"
    },
    "desc": {
      "zh": "对应API的className，默认值：-"
    },
    "showDes": true
  },
  {
    "name": "className",
    "type": "String",
    "defaultValue": null,
    "groupName": "自定义样式",
    "hidePropBy": {
      "name": "enabledClassName",
      "includeEmpty": true,
      "values": [
        false
      ]
    },
    "locale": {
      "zh": "类值"
    },
    "desc": {
      "zh": "多个类值请使用空格分隔"
    },
    "showDes": true,
    "placeholder": "任意字符串"
  }
]